Workbook

Sheet Historical_IS
A1: Particulars | B1: FY26 | C1: FY25 | D1: FY24 | E1: FY23 | F1: FY22 | G1: FY21
A2: Revenue from Operations | B2: 267021 | C2: 255324 | D2: 240893 | E2: 225458 | F2: 191754 | G2: 164177
A3: Employee Cost | B3: 154994 | C3: 145788 | D3: 140131 | E3: 127522 | F3: 107554 | G3: 91814
A4: Other Operating Cost | B4: 45189 | C4: 47371 | D4: 41451 | E4: 43699 | F4: 35747 | G4: 29882
A5: Total Operating Cost | B5: 200183 | C5: 193159 | D5: 181582 | E5: 171221 | F5: 143301 | G5: 121696
A6: EBIT (Operating Income) | B6: 66838 | C6: 62165 | D6: 59311 | E6: 54237 | F6: 48453 | G6: 42481
A7: Profit Before Tax | B7: 70355 | C7: 65331 | D7: 63038 | E7: 56907 | F7: 51687 | G7: 44978
A8: Profit After Tax | B8: 52820 | C8: 48553 | D8: 46585 | E8: 42147 | F8: 38327 | G8: 33388
A9: EPS (₹) | B9: 145.99 | C9: 134.19 | D9: 127.74 | E9: 115.19 | F9: 103.62 | G9: 89.27

Sheet Historical_BS
A1: Particulars | B1: FY26 | C1: FY25 | D1: FY24 | E1: FY23 | F1: FY22 | G1: FY21
A2: PPE (Owned & Leased, Net) | B2: 13441 | C2: 12407 | D2: 10805 | E2: 11336 | F2: 11797 | G2: 11874
A3: Intangible Assets & Goodwill | B3: 9284 | C3: 2800 | D3: 2342 | E3: 2725 | F3: 2888 | G3: 2278
A4: Invested Funds | B4: 50020 | C4: 47222 | D4: 46963 | E4: 49824 | F4: 56053 | G4: 50430
A5: Business Assets (Net) | B5: 34495 | C5: 32327 | D5: 30379 | E5: 26539 | F5: 18401 | G5: 21851
A6: Net Worth | B6: 107240 | C6: 94756 | D6: 90489 | E6: 90424 | F6: 89139 | G6: 86433

Sheet Balance sheet
A1: BALANCE SHEET
A4: Particulars | B4: FY26 | C4: FY25 | D4: FY24 | E4: FY23 | F4: FY22 | G4: FY21
A5: Non-Current Assets
A6: Property, Plant & Equipment | B6: 11032 | C6: 10978 | D6: 11648 | E6: 10467 | F6: 9634 | G6: 8702
A7: Capital Work-in-Progress | B7: 2665 | C7: 1546 | D7: 643 | E7: 482 | F7: 330 | G7: 221
A8: Right-of-use Assets | B8: 11027 | C8: 9275 | D8: 4210 | E8: 4036 | F8: 3949 | G8: 4015
A9: Goodwill | B9: 9108 | C9: 1860 | D9: 5755 | E9: 5571 | F9: 5298 | G9: 4947
A10: Other Intangible Assets | B10: 176 | C10: 940 | D10: 2036 | E10: 2194 | F10: 2506 | G10: 2635
A11: Investments | B11: 218 | C11: 275 | D11: 11745 | E11: 14938 | F11: 13249 | G11: 8421
A12: Trade Receivables (Billed + Unbilled) | B12: 213 | C12: 129 | D12: 2530 | E12: 2215 | F12: 1588 | G12: 1221
A13: Loans | B13: 775 | C13: 25 | D13: 1526 | E13: 1353 | F13: 1027 | G13: 756
A14: Other Financial Assets | B14: 2944 | C14: 2731 | D14: 8862 | E14: 7413 | F14: 7445 | G14: 5370
A15: Deferred Tax Assets (Net) | B15: 4465 | C15: 3578 | D15: 5159 | E15: 5195 | F15: 4934 | G15: 4099
A16: Income Tax Assets (Net) | B16: 1439 | C16: 1569 | D16: 4164 | E16: 4173 | F16: 3715 | G16: 2917
A17: Other Non-Current Assets | B17: 2605 | C17: 3712 | D17: 2270 | E17: 1879 | F17: 1760 | G17: 1571
A18: Total Non-current Assets | B18: =SUM(B6:B17) -> 46667 | C18: =SUM(C6:C17) -> 36618 | D18: =SUM(D6:D17) -> 60548 | E18: =SUM(E6:E17) -> 59916 | F18: =SUM(F6:F17) -> 55435 | G18: =SUM(G6:G17) -> 44875
A20: Current Assets
A21: Inventories | B21: 29 | C21: 21 | D21: 29 | E21: 27 | F21: 19 | G21: 7
A22: Investments | B22: 33770 | C22: 30689 | D22: 44902 | E22: 35738 | F22: 29262 | G22: 28324
A23: Trade Receivables (Billed + Unbilled) | B23: 67714 | C23: 59046 | D23: 44147 | E23: 42798 | F23: 36102 | G23: 30621
A24: Cash & Cash Equivalents | B24: 6417 | C24: 8342 | D24: 4907 | E24: 1462 | F24: 8197 | G24: 1112
A25: Other Bank Balances | B25: 6491 | C25: 7121 | D25: 8370 | E25: 3081 | F25: 5495 | G25: 2030
A26: Loans | B26: 1659 | C26: 9 | D26: 381 | E26: 332 | F26: 5653 | G26: 10486
A27: Other Financial Assets | B27: 1833 | C27: 2742 | D27: 1790 | E27: 1557 | F27: 1432 | G27: 1363
A28: Income Tax Assets (Net) | B28: 1259 | C28: 257 | D28: – | E28: – | F28: – | G28: –
A29: Other Current Assets | B29: 16533 | C29: 14784 | D29: 9084 | E29: 7789 | F29: 8032 | G29: 9217
A30: Total Current Assets | B30: =SUM(B21:B29) -> 135705 | C30: =SUM(C21:C29) -> 123011 | D30: =SUM(D21:D29) -> 113610 | E30: =SUM(E21:E29) -> 92784 | F30: =SUM(F21:F29) -> 94192 | G30: =SUM(G21:G29) -> 83160
A32: Total Assets | B32: =B18+B30 -> 182372 | C32: =C18+C30 -> 159629 | D32: =D18+D30 -> 174158 | E32: =E18+E30 -> 152700 | F32: =F18+F30 -> 149627 | G32: =G18+G30 -> 128035
A34: Particulars | B34: FY26 | C34: FY25 | D34: FY24 | E34: FY23 | F34: FY22 | G34: FY21
A35: Equity
A36: Non-Controlling Interests | B36: 1238 | C36: 1015 | D36: 25 | E36: 19 | F36: 16 | G36: 16
A37: Share Capital | B37: 362 | C37: 362 | D37: 362 | E37: 362 | F37: 362 | G37: 362
A38: Other Equity | B38: 106878 | C38: 94394 | D38: 156529 | E38: 136431 | F38: 127547 | G38: 114778
A39: Total Equity | B39: =SUM(B36:B38) -> 108478 | C39: =SUM(C36:C38) -> 95771 | D39: =SUM(D36:D38) -> 156916 | E39: =SUM(E36:E38) -> 136812 | F39: =SUM(F36:F38) -> 127925 | G39: =SUM(G36:G38) -> 115156
A41: Non-current Liabilities
A42: Borrowings | B42: 0 | C42: 0 | D42: 0 | E42: 0 | F42: 0 | G42: 0
A43: Class B Compulsorily Convertible Preference Shares | B43: 126 | C43: 0 | D43: 0 | E43: 0 | F43: 0 | G43: 0
A44: Lease Liabilities | B44: 9453 | C44: 7838 | D44: 3765 | E44: 3652 | F44: 3708 | G44: 3814
A45: Other Non-Current Liabilities (Other Financial Liabilities + Employee Benefits + Unearned & Deferred Revenue) | B45: 2196 | C45: 2039 | D45: 2094 | E45: 2271 | F45: 2123 | G45: 1796
A46: Deferred Tax Liabilities (Net) | B46: 1205 | C46: 980 | D46: 0 | E46: 0 | F46: 0 | G46: 0
A47: Total Non-current Liabilities | B47: =SUM(B42:B46) -> 12980 | C47: =SUM(C42:C46) -> 10857 | D47: =SUM(D42:D46) -> 5859 | E47: =SUM(E42:E46) -> 5923 | F47: =SUM(F42:F46) -> 5831 | G47: =SUM(G42:G46) -> 5610
A49: Current Liabilities
A50: Trade Payables | B50: 14808 | C50: 13909 | D50: 8369 | E50: 8158 | F50: 7466 | G50: 6313
A51: Other Financial Liabilities | B51: 11194 | C51: 8542 | D51: 15058 | E51: 12852 | F51: 11494 | G51: 10388
A52: Lease Liabilities | B52: 1830 | C52: 1554 | D52: 1839 | E52: 1712 | F52: 1627 | G52: 1592
A53: Other Current Liabilities (Unearned & Deferred Revenue + Other Liabilities + Provisions + Employee Benefit Obligations) | B53: 18331 | C53: 16281 | D53: 42117 | E53: 34412 | F53: 33909 | G53: 28136
A54: Income Tax Liabilities (Net) | B54: 14751 | C54: 12715 | D54: 5538 | E54: 4831 | F54: 3375 | G54: 3840
A55: Total Current Liabilities | B55: =SUM(B50:B54) -> 60914 | C55: =SUM(C50:C54) -> 53001 | D55: =SUM(D50:D54) -> 72921 | E55: =SUM(E50:E54) -> 61965 | F55: =SUM(F50:F54) -> 57871 | G55: =SUM(G50:G54) -> 50269
A57: Total Liabilities | B57: =B47+B55 -> 73894 | C57: =C47+C55 -> 63858 | D57: =D47+D55 -> 78780 | E57: =E47+E55 -> 67888 | F57: =F47+F55 -> 63702 | G57: =G47+G55 -> 55879
A58: Total Equity & Liabilities | B58: =B39+B57 -> 182372 | C58: =C39+C57 -> 159629 | D58: =D39+D57 -> 235696 | E58: =E39+E57 -> 204700 | F58: =F39+F57 -> 191627 | G58: =G39+G57 -> 171035

Sheet Cash Flow
A1: CASH FLOW STATEMENT
A4: CASH FLOWS FROM OPERATING ACTIVITIES
A5: Particulars | B5: FY26 | C5: FY25 | D5: FY24 | E5: FY23 | F5: FY22 | G5: FY21
A6: Profit for the year | B6: 49454 | C6: 48797 | D6: 46099 | E6: 42303 | F6: 38449 | G6: 32562
A7: Adjustments for:
A8: Depreciation and amortisation expense | B8: 5560 | C8: 5242 | D8: 4985 | E8: 5022 | F8: 4604 | G8: 4065
A9: Bad debts and advances written off, allowance for expected credit losses and doubtful advances (net) | B9: 184 | C9: 128 | D9: 114 | E9: 140 | F9: 135 | G9: 201
A10: Provision towards legal claim | B10: 1010 | C10: - | D10: - | E10: - | F10: - | G10: 1218
A11: Provision towards restructuring expenses | B11: 120 | C11: - | D11: - | E11: - | F11: - | G11: -
A12: Tax expense | B12: 16033 | C12: 16534 | D12: 15898 | E12: 14604 | F12: 13238 | G12: 11198
A13: Net gain on lease modification | B13: -110 | C13: -15 | D13: -7 | E13: 2 | F13: -7 | G13: -100
A14: Net gain on sub-lease | B14: -8 | C14: - | D14: - | E14: - | F14: 9 | G14: -
A15: Unrealised foreign exchange gain | B15: -176 | C15: -1 | D15: -17 | E15: -189 | F15: -120 | G15: -21
A16: Net gain on disposal of property, plant and equipment | B16: -17 | C16: -20 | D16: -7 | E16: -26 | F16: -23 | G16: -13
A17: Net gain on disposal / fair valuation of investments | B17: -701 | C17: -269 | D17: -312 | E17: -224 | F17: -198 | G17: -204
A18: Net gain on fair valuation of call option | B18: -17 | C18: - | D18: - | E18: - | F18: - | G18: -
A19: Transaction cost on incorporation of subsidiary | B19: 18 | C19: - | D19: - | E19: - | F19: - | G19: -
A20: Interest income | B20: -3854 | C20: -3296 | D20: -3781 | E20: -3248 | F20: -2663 | G20: -2504
A21: Dividend income | B21: -35 | C21: -43 | D21: -41 | E21: -15 | F21: -4 | G21: -8
A22: Finance costs | B22: 1227 | C22: 796 | D22: 778 | E22: 779 | F22: 784 | G22: 637
A23: Operating profit before working capital changes | B23: =SUM(B8:B22,B6) -> 68688 | C23: =SUM(C8:C22,C6) -> 67853 | D23: =SUM(D8:D22,D6) -> 63709 | E23: =SUM(E8:E22,E6) -> 59148 | F23: =SUM(F8:F22,F6) -> 54204 | G23: =SUM(G8:G22,G6) -> 47031
A24: Net change in
A25: Inventories | B25: -8 | C25: 7 | D25: - | E25: -8 | F25: -12 | G25: -3
A26: Trade receivables – Billed | B26: -4778 | C26: -5519 | D26: -3327 | E26: -6501 | F26: -4210 | G26: 1260
A27: Trade receivables – Unbilled | B27: -470 | C27: 291 | D27: -5 | E27: -1182 | F27: -934 | G27: -201
A28: Loans and other financial assets | B28: 197 | C28: -738 | D28: -301 | E28: 261 | F28: -116 | G28: -17
A29: Other assets | B29: 837 | C29: -2552 | D29: -3160 | E29: -25 | F29: 807 | G29: -2805
A30: Trade payables | B30: -1105 | C30: 3718 | D30: -632 | E30: 2036 | F30: 186 | G30: -93
A31: Unearned and deferred revenue | B31: 320 | C31: 395 | D31: -740 | E31: 39 | F31: -103 | G31: 1091
A32: Other financial liabilities | B32: 2814 | C32: -119 | D32: -695 | E32: 1417 | F32: 1153 | G32: 122
A33: Other liabilities and provisions | B33: -17 | C33: 1158 | D33: 1978 | E33: -254 | F33: 460 | G33: 1509
A34: Cash flows generated from operations | B34: =SUM(B25:B33) -> -2210 | C34: =SUM(C25:C33) -> -3359 | D34: =SUM(D25:D33) -> -6882 | E34: =SUM(E25:E33) -> -4217 | F34: =SUM(F25:F33) -> -2769 | G34: =SUM(G25:G33) -> 863
A35: Taxes paid (net of refunds) | B35: -14384 | C35: -15586 | D35: -12489 | E35: -12966 | F35: -11486 | G35: -9092
A36: Net cash flows generated from operating activities | B36: =B23+B34+B35 -> 52094 | C36: =C23+C34+C35 -> 48908 | D36: =D23+D34+D35 -> 44338 | E36: =E23+E34+E35 -> 41965 | F36: =F23+F34+F35 -> 39949 | G36: =G23+G34+G35 -> 38802
A38: CASH FLOWS FROM INVESTING ACTIVITIES
A41: Particulars | B41: FY26 | C41: FY25 | D41: FY24 | E41: FY23 | F41: FY22 | G41: FY21
A42: Bank deposits placed | B42: -8506 | C42: -10496 | D42: -9471 | E42: -4548 | F42: -15947 | G42: -6605
A43: Inter-corporate deposits placed | B43: -1500 | C43: - | D43: - | E43: -8293 | F43: -14619 | G43: -21076
A44: Purchase of investments (including reverse repo) | B44: -151864 | C44: -145962 | D44: -141011 | E44: -129745 | F44: -75374 | G44: -54462
A45: Payment for purchase of property, plant and equipment | B45: -3670 | C45: -2917 | D45: -2202 | E45: -2532 | F45: -2483 | G45: -2719
A46: Payment including advances for acquiring right-of-use assets | B46: -109 | C46: -76 | D46: -30 | E46: -213 | F46: -15 | G46: -101
A47: Payment for purchase of intangible assets | B47: -367 | C47: -944 | D47: -442 | E47: -355 | F47: -497 | G47: -356
A48: Earmarked deposits placed with banks | B48: -530 | C48: - | D48: - | E48: - | F48: - | G48: -
A49: Acquisition of assets | B49: -554 | C49: -1063 | D49: - | E49: - | F49: - | G49: -
A50: Acquisition of subsidiaries (net of cash of ₹130 crore) | B50: -6750 | C50: - | D50: - | E50: - | F50: - | G50: -
A51: Advance towards acquisition of investment | B51: -250 | C51: - | D51: - | E51: - | F51: - | G51: -
A52: Proceeds from bank deposits | B52: 9259 | C52: 8177 | D52: 8089 | E52: 6252 | F52: 11950 | G52: 4767
A53: Proceeds from inter-corporate deposits | B53: - | C53: 170 | D53: 846 | E53: 13654 | F53: 19498 | G53: 18018
A54: Proceeds from disposal / redemption of investments | B54: 148023 | C54: 147695 | D54: 147204 | E54: 122687 | F54: 73852 | G54: 51630
A55: Proceeds from sub-lease receivable | B55: 9 | C55: 5 | D55: 3 | E55: 2 | F55: 3 | G55: -
A56: Proceeds from disposal of property, plant and equipment | B56: 65 | C56: 23 | D56: 17 | E56: 37 | F56: 31 | G56: 37
A57: Proceeds from earmarked deposits | B57: 825 | C57: - | D57: - | E57: - | F57: - | G57: -
A58: Interest received | B58: 3008 | C58: 3056 | D58: 2990 | E58: 3080 | F58: 2700 | G58: 2730
A59: Dividend received | B59: 84 | C59: 40 | D59: 26 | E59: 13 | F59: 4 | G59: 8
A60: Loan given | B60: - | C60: -29 | D60: - | E60: - | F60: - | G60: -
A61: Loan recovered | B61: - | C61: 3 | D61: - | E61: - | F61: - | G61: -
A62: Transaction cost on incorporation of subsidiary | B62: -18 | C62: - | D62: - | E62: - | F62: - | G62: -
A63: Net cash flows used in investing activities | B63: =SUM(B42:B62) -> -12845 | C63: =SUM(C42:C62) -> -2318 | D63: =SUM(D42:D62) -> 6019 | E63: =SUM(E42:E62) -> 39 | F63: =SUM(F42:F62) -> -897 | G63: =SUM(G42:G62) -> -8129
A65: CASH FLOWS FROM FINANCING ACTIVITIES
A68: Particulars | B68: FY26 | C68: FY25 | D68: FY24 | E68: FY23 | F68: FY22 | G68: FY21
A69: Repayment of lease liabilities | B69: -1861 | C69: -1664 | D69: -1624 | E69: -1554 | F69: -1474 | G69: -1345
A70: Interest paid | B70: -901 | C70: -840 | D70: -748 | E70: -760 | F70: -768 | G70: -624
A71: Dividend paid | B71: -39437 | C71: -44864 | D71: -42628 | E71: -41440 | F71: -38246 | G71: -32925
A72: Dividend paid to non-controlling interests | B72: -134 | C72: -98 | D72: -82 | E72: -65 | F72: -58 | G72: -53
A73: Sale of shares to non-controlling interests | B73: - | C73: 28 | D73: - | E73: - | F73: - | G73: -
A74: Issue of equity shares to non-controlling interests | B74: 3 | C74: - | D74: - | E74: - | F74: - | G74: -
A75: Issue of Class A compulsorily convertible preference shares to non-controlling interests | B75: 71 | C75: - | D75: - | E75: - | F75: - | G75: -
A76: Issue of Class B compulsorily convertible preference shares | B76: 126 | C76: - | D76: - | E76: - | F76: - | G76: -
A77: Net cash flows used in financing activities | B77: =SUM(B69:B76) -> -42133 | C77: =SUM(C69:C76) -> -47438 | D77: =SUM(D69:D76) -> -45082 | E77: =SUM(E69:E76) -> -43819 | F77: =SUM(F69:F76) -> -40546 | G77: =SUM(G69:G76) -> -34947
A79: NET MOVEMENT IN CASH
A82: Particulars | B82: FY26 | C82: FY25 | D82: FY24 | E82: FY23 | F82: FY22 | G82: FY21
A83: Net change in cash and cash equivalents | B83: -2884 | C83: -848 | D83: 5282 | E83: -1815 | F83: -1494 | G83: -4274
A84: Cash and cash equivalents at the beginning of the year | B84: 8342 | C84: 9016 | D84: 3060 | E84: 4884 | F84: 6415 | G84: 10691
A85: Exchange difference on translation of foreign currency cash and cash equivalents | B85: 959 | C85: 174 | D85: 565 | E85: -9 | F85: -37 | G85: -2
A86: Cash and cash equivalents at the end of the year | B86: =SUM(B83:B85) -> 6417 | C86: =SUM(C83:C85) -> 8342 | D86: =SUM(D83:D85) -> 8907 | E86: =SUM(E83:E85) -> 3060 | F86: =SUM(F83:F85) -> 4884 | G86: =SUM(G83:G85) -> 6415
A88: COMPONENTS OF CASH & CASH EQUIVALENTS
A91: Particulars | B91: FY26 | C91: FY25 | D91: FY24 | E91: FY23 | F91: FY22 | G91: FY21
A92: In current accounts | B92: 3193 | C92: 3421 | D92: 3823 | E92: 1590 | F92: 2747 | G92: 2522
A93: In deposit accounts | B93: 3217 | C93: 4907 | D93: 4907 | E93: 1462 | F93: 1959 | G93: 1112
A94: Cheques on hand | B94: * | C94: * | D94: * | E94: * | F94: * | G94: *
A95: Cash on hand | B95: * | C95: * | D95: * | E95: * | F95: * | G95: *
A96: Remittances in transit | B96: 7 | C96: 14 | D96: 177 | E96: 8 | F96: 178 | G96: 2781
A97: Total Cash & Cash Equivalents | B97: =SUM(B92:B96) -> 6417 | C97: =SUM(C92:C96) -> 8342 | D97: =SUM(D92:D96) -> 8907 | E97: =SUM(E92:E96) -> 3060 | F97: =SUM(F92:F96) -> 4884 | G97: =SUM(G92:G96) -> 6415
D660: should I post both or just 1, god I am too nervous
D807: I removed emogis, I am a genz but emogis just annoy me
D886: now what?
D922: you mean change this?
D1038: NOW GIMME CODE THE REST THREE
D1074: bass ab aur koi graph grooph nai khelungi
D1111: this I did 30 minutes ago now you gimme 72 columned dataset
D1218: GemDataEXTR.zip
D1219: Zip Archive
D1257: for second code, (31,200)
D1279: capgemini.pdf
D1280: PDF
... D2199: So I'd change the Income Statement to this:
D2201: Particulars | E2201: FY26 | F2201: FY25 | G2201: FY24 | H2201: FY23 | I2201: FY22 | J2201: FY21
D2202: Revenue from Operations | E2202: 267021 | F2202: 255324 | G2202: 240893 | H2202: 225458 | I2202: 191754 | J2202: 164177
D2203: Other Income | E2203: 4402 | F2203: 3962
D2204: Total Income | E2204: 271423 | F2204: 259286
...

Sheet Ratio analysis
A1: RATIO ANALYSIS SHEET
A3: Ratios | B3: Formula | C3: FY26 | D3: FY25 | E3: FY24 | F3: FY23 | G3: FY22 | H3: FY21 | I3: Benchmark | J3: Comment
A4: PROFITABILITY RATIOS
A5: Revenue Growth | B5: (Current Revenue - Previous Revenue)/ Previous Revenue | C5: =(Historical_IS!B2-Historical_IS!C2)/Historical_IS!C2 -> 0.04581238 | D5: =(Historical_IS!C2-Historical_IS!D2)/Historical_IS!D2 -> 0.059906265 | E5: =(Historical_IS!D2-Historical_IS!E2)/Historical_IS!E2 -> 0.068460645 | F5: =(Historical_IS!E2-Historical_IS!F2)/Historical_IS!F2 -> 0.17576687 | G5: =(Historical_IS!F2-Historical_IS!G2)/Historical_IS!G2 -> 0.16797115 | I5: 0.08 | J5: =IF(C5>I5,"Above Benchmark", IF(C5<I5,"Below Benchmark","At Benchmark")) -> Below Benchmark
A6: EBIT Margin | B6: EBIT / Revenue | C6: =Historical_IS!B6/Historical_IS!B2 -> 0.2503099 | D6: =Historical_IS!C6/Historical_IS!C2 -> 0.24347496 | E6: =Historical_IS!D6/Historical_IS!D2 -> 0.24621305 | F6: =Historical_IS!E6/Historical_IS!E2 -> 0.24056365 | G6: =Historical_IS!F6/Historical_IS!F2 -> 0.25268313 | H6: =Historical_IS!G6/Historical_IS!G2 -> 0.25875123 | I6: 0.22 | J6: =IF(C6>I6,"Above Benchmark", IF(C6<I6,"Below Benchmark","At Benchmark")) -> Above Benchmark
A7: Net Profit Margin | B7: PAT / Revenue | C7: =Historical_IS!B8/Historical_IS!B2 -> 0.19781216 | D7: =Historical_IS!C8/Historical_IS!C2 -> 0.1901623 | E7: =Historical_IS!D8/Historical_IS!D2 -> 0.19338461 | F7: =Historical_IS!E8/Historical_IS!E2 -> 0.18693947 | G7: =Historical_IS!F8/Historical_IS!F2 -> 0.19987588 | H7: =Historical_IS!G8/Historical_IS!G2 -> 0.20336588 | I7: 0.18 | J7: =IF(C7>I7,"Above Benchmark", IF(C7<I7,"Below Benchmark","At Benchmark")) -> Above Benchmark
A8: Operating Cost Ratio | B8: Operating Cost / Revenue | C8: =Historical_IS!B5/Historical_IS!B2 -> 0.7496901 | D8: =Historical_IS!C5/Historical_IS!C2 -> 0.75652504 | E8: =Historical_IS!D5/Historical_IS!D2 -> 0.75378695 | F8: =Historical_IS!E5/Historical_IS!E2 -> 0.75943635 | G8: =Historical_IS!F5/Historical_IS!F2 -> 0.74731687 | H8: =Historical_IS!G5/Historical_IS!G2 -> 0.74124877 | I8: 0.78 | J8: =IF(C8<I33, "Better than Benchmark", IF(C8>I8,"Worse than Benchmark", "At Benchmark")) -> At Benchmark
A9: Employee Cost Ratio | B9: Employee Cost / Revenue | C9: =Historical_IS!B3/Historical_IS!B2 -> 0.58045622 | D9: =Historical_IS!C3/Historical_IS!C2 -> 0.57099215 | E9: =Historical_IS!D3/Historical_IS!D2 -> 0.5817147 | F9: =Historical_IS!E3/Historical_IS!E2 -> 0.56561311 | G9: =Historical_IS!F3/Historical_IS!F2 -> 0.56089573 | H9: =Historical_IS!G3/Historical_IS!G2 -> 0.5592379 | I9: 0.55 | J9: =IF(C9<I34, "Better than Benchmark", IF(C9>I9,"Worse than Benchmark", "At Benchmark")) -> Worse than Benchmark
A10: Other Operating Cost Ratio | B10: Other Operating Cost / Revenue | C10: =Historical_IS!B4/Historical_IS!B2 -> 0.16923388 | D10: =Historical_IS!C4/Historical_IS!C2 -> 0.18553289 | E10: =Historical_IS!D4/Historical_IS!D2 -> 0.17207225 | F10: =Historical_IS!E4/Historical_IS!E2 -> 0.19382324 | G10: =Historical_IS!F4/Historical_IS!F2 -> 0.18642114 | H10: =Historical_IS!G4/Historical_IS!G2 -> 0.18201088 | I10: 0.23 | J10: =IF(C10<I35, "Better than Benchmark", IF(C10>I10,"Worse than Benchmark", "At Benchmark")) -> Better than Benchmark
A11: Effective Tax Rate | B11: Tax Expense / PBT | C11: =(Historical_IS!B7-Historical_IS!B8)/Historical_IS!B7 -> 0.24923602 | D11: =(Historical_IS!C7-Historical_IS!C8)/Historical_IS!C7 -> 0.25681529 | E11: =(Historical_IS!D7-Historical_IS!D8)/Historical_IS!D7 -> 0.2610013 | F11: =(Historical_IS!E7-Historical_IS!E8)/Historical_IS!E7 -> 0.25937055 | G11: =(Historical_IS!F7-Historical_IS!F8)/Historical_IS!F7 -> 0.25847892 | H11: =(Historical_IS!G7-Historical_IS!G8)/Historical_IS!G7 -> 0.25768153 | I11: 0.23 | J11: =IF(C11<I36, "Better than Benchmark", IF(C11>I11,"Worse than Benchmark", "At Benchmark")) -> Better than Benchmark
A12: EBITDA Margin | B12: EBITDA / Revenue | C12: =(Historical_IS!B6+'Cash Flow'!B8)/Historical_IS!B2 -> 0.27113223 | D12: =(Historical_IS!C6+'Cash Flow'!C8)/Historical_IS!C2 -> 0.26400573 | E12: =(Historical_IS!D6+'Cash Flow'!D8)/Historical_IS!D2 -> 0.26690688 | F12: =(Historical_IS!E6+'Cash Flow'!E8)/Historical_IS!E2 -> 0.26283831 | G12: =(Historical_IS!F6+'Cash Flow'!F8)/Historical_IS!F2 -> 0.27669305 | H12: =(Historical_IS!G6+'Cash Flow'!G8)/Historical_IS!G2 -> 0.28351109
A14: LIQUIDITY RATIOS
A15: Ratios | B15: Formula | C15: FY26 | D15: FY25 | E15: FY24 | F15: FY23 | G15: FY22 | H15: FY21 | I15: Benchmark | J15: Comment
A16: Current Ratio | B16: Current Assets/Current Liabilities | C16: ='Balance sheet'!B30/'Balance sheet'!B55 -> 2.227813 | D16: ='Balance sheet'!C30/'Balance sheet'!C55 -> 2.3209185 | E16: ='Balance sheet'!D30/'Balance sheet'!D55 -> 1.5579874 | F16: ='Balance sheet'!E30/'Balance sheet'!E55 -> 1.4973614 | G16: ='Balance sheet'!F30/'Balance sheet'!F55 -> 1.6276201 | H16: ='Balance sheet'!G30/'Balance sheet'!G55 -> 1.6542999 | I16: 2.5 | J16: =IF(C16>I16,"Above Benchmark", IF(C16<I16,"Below Benchmark","At Benchmark")) -> Below Benchmark
A17: Quick Ratio | B17: (Current Assets - Inventory)/Current Liabilities | C17: =('Balance sheet'!B30-'Balance sheet'!B21)/'Balance sheet'!B55 -> 2.2273369 | D17: =('Balance sheet'!C30-'Balance sheet'!C21)/'Balance sheet'!C55 -> 2.3205223 | E17: =('Balance sheet'!D30-'Balance sheet'!D21)/'Balance sheet'!D55 -> 1.5575897 | F17: =('Balance sheet'!E30-'Balance sheet'!E21)/'Balance sheet'!E55 -> 1.4969257 | G17: =('Balance sheet'!F30-'Balance sheet'!F21)/'Balance sheet'!F55 -> 1.6272917 | H17: =('Balance sheet'!G30-'Balance sheet'!G21)/'Balance sheet'!G55 -> 1.6541606 | I17: 2.3 | J17: =IF(C17>I17,"Above Benchmark", IF(C17<I17,"Below Benchmark","At Benchmark")) -> Below Benchmark
A18: Cash Ratio | B18: Cash & Cash Equivalents/Current Liabilities | C18: ='Balance sheet'!B24/'Balance sheet'!B55 -> 0.10534524 | D18: ='Balance sheet'!C24/'Balance sheet'!C55 -> 0.15739326 | E18: ='Balance sheet'!D24/'Balance sheet'!D55 -> 0.067292001 | F18: ='Balance sheet'!E24/'Balance sheet'!E55 -> 0.023593964 | G18: ='Balance sheet'!F24/'Balance sheet'!F55 -> 0.14164262 | H18: ='Balance sheet'!G24/'Balance sheet'!G55 -> 0.022120989 | I18: 1.5 | J18: =IF(C18>I18,"Above Benchmark", IF(C18<I18,"Below Benchmark","At Benchmark")) -> Below Benchmark
A19: Working Capital | B19: Current Assets-Current Liabilities | C19: ='Balance sheet'!B30-'Balance sheet'!B55 -> 74791 | D19: ='Balance sheet'!C30-'Balance sheet'!C55 -> 70010 | E19: ='Balance sheet'!D30-'Balance sheet'!D55 -> 40689 | F19: ='Balance sheet'!E30-'Balance sheet'!E55 -> 30819 | G19: ='Balance sheet'!F30-'Balance sheet'!F55 -> 36321 | H19: ='Balance sheet'!G30-'Balance sheet'!G55 -> 32891 | I19: Positive | J19: =IF(C19>0,"Healthy", IF(C19<0, "Negative","Break-even")) -> Healthy
A20: Working Capital Ratio | B20: Working Capital/Revenue | C20: =C19/Historical_IS!B2 -> 0.28009407 | D20: =D19/Historical_IS!C2 -> 0.27420062 | E20: =E19/Historical_IS!D2 -> 0.16890902 | F20: =F19/Historical_IS!E2 -> 0.13669508 | G20: =G19/Historical_IS!F2 -> 0.18941456 | H20: =H19/Historical_IS!G2 -> 0.20033866 | I20: 2 | J20: =IF(C20>I20,"Above Benchmark", IF(C20<I20,"Below Benchmark","At Benchmark")) -> Below Benchmark
A22: EFFICIENCY RATIOS
A23: Ratios | B23: Formula | C23: FY26 | D23: FY25 | E23: FY24 | F23: FY23 | G23: FY22 | H23: FY21 | I23: Benchmark | J23: Comment
A24: Total Asset Turnover | B24: Revenue/Average Total Assets | C24: =Historical_IS!B2/AVERAGE('Balance sheet'!B32,'Balance sheet'!C32) -> 1.5615217 | D24: =Historical_IS!C2/AVERAGE('Balance sheet'!C32,'Balance sheet'!D32) -> 1.5298619 | E24: =Historical_IS!D2/AVERAGE('Balance sheet'!D32,'Balance sheet'!E32) -> 1.4739918 | F24: =Historical_IS!E2/AVERAGE('Balance sheet'!E32,'Balance sheet'!F32) -> 1.4914844 | G24: =Historical_IS!F2/AVERAGE('Balance sheet'!F32,'Balance sheet'!G32) -> 1.3812045 | H24: =Historical_IS!G2/AVERAGE('Balance sheet'!G32,'Balance sheet'!H32) -> 1.2822822 | I24: 1.3 | J24: =IF(C24>I24,"Above Benchmark", IF(C24<I24,"Below Benchmark","At Benchmark")) -> Above Benchmark
A25: Fixed Asset Turnover | B25: Revenue/Average PPE | C25: =Historical_IS!B2/AVERAGE(Historical_BS!B2,Historical_BS!C2) -> 20.660864 | D25: =Historical_IS!C2/AVERAGE(Historical_BS!C2,Historical_BS!D2) -> 21.999311 | E25: =Historical_IS!D2/AVERAGE(Historical_BS!D2,Historical_BS!E2) -> 21.759902 | F25: =Historical_IS!E2/AVERAGE(Historical_BS!E2,Historical_BS!F2) -> 19.492327 | G25: =Historical_IS!F2/AVERAGE(Historical_BS!F2,Historical_BS!G2) -> 16.201597 | H25: =Historical_IS!G2/AVERAGE(Historical_BS!G2,Historical_BS!H2) -> 13.826596 | I25: 15 | J25: =IF(C25>I25,"Above Benchmark", IF(C25<I25,"Below Benchmark","At Benchmark")) -> Above Benchmark
A26: Receivable Days | B26: Average Trade Receivables/Revenue from Operation*365 | C26: =AVERAGE('Balance sheet'!B23,'Balance sheet'!C23)/Historical_IS!B2*365 -> 86.636257 | D26: =AVERAGE('Balance sheet'!C23,'Balance sheet'!D23)/Historical_IS!C2*365 -> 73.760095 | E26: =AVERAGE('Balance sheet'!D23,'Balance sheet'!E23)/Historical_IS!D2*365 -> 65.869338 | F26: =AVERAGE('Balance sheet'!E23,'Balance sheet'!F23)/Historical_IS!E2*365 -> 63.866663 | G26: =AVERAGE('Balance sheet'!F23,'Balance sheet'!G23)/Historical_IS!F2*365 -> 63.502965 | H26: =AVERAGE('Balance sheet'!G23,'Balance sheet'!H23)/Historical_IS!G2*365 -> 68.076923 | I26: 70 | J26: =IF(C26<I51, "Better than Benchmark", IF(C26>I26,"Worse than Benchmark", "At Benchmark")) -> Worse than Benchmark
A27: Inventory Days | B27: Average Inventory/Operating Cost×365 | C27: =AVERAGE('Balance sheet'!B21,'Balance sheet'!C21)/Historical_IS!B5*365 -> 0.045583291 | D27: =AVERAGE('Balance sheet'!C21,'Balance sheet'!D21)/Historical_IS!C5*365 -> 0.047240874 | E27: =AVERAGE('Balance sheet'!D21,'Balance sheet'!E21)/Historical_IS!D5*365 -> 0.056283112 | F27: =AVERAGE('Balance sheet'!E21,'Balance sheet'!F21)/Historical_IS!E5*365 -> 0.049030201 | G27: =AVERAGE('Balance sheet'!F21,'Balance sheet'!G21)/Historical_IS!F5*365 -> 0.033112121 | H27: =AVERAGE('Balance sheet'!G21,'Balance sheet'!H21)/Historical_IS!G5*365 -> 0.020994938 | I27: 5 | J27: =IF(C27<I52, "Better than Benchmark", IF(C27>I27,"Worse than Benchmark", "At Benchmark")) -> Better than Benchmark
A28: Payable Days | B28: Average Trade Payables/Operating Cost×365 | C28: =AVERAGE('Balance sheet'!B23,'Balance sheet'!C23)/Historical_IS!B5*365 -> 115.56276 | D28: =AVERAGE('Balance sheet'!C23,'Balance sheet'!D23)/Historical_IS!C5*365 -> 97.49855 | E28: =AVERAGE('Balance sheet'!D23,'Balance sheet'!E23)/Historical_IS!D5*365 -> 87.384556 | F28: =AVERAGE('Balance sheet'!E23,'Balance sheet'!F23)/Historical_IS!E5*365 -> 84.097453 | G28: =AVERAGE('Balance sheet'!F23,'Balance sheet'!G23)/Historical_IS!F5*365 -> 84.974616 | H28: =AVERAGE('Balance sheet'!G23,'Balance sheet'!H23)/Historical_IS!G5*365 -> 91.840858 | I28: 25 | J28: =IF(C28<I53, "Better than Benchmark", IF(C28>I28,"Worse than Benchmark", "At Benchmark")) -> Worse than Benchmark
A29: Cash Conversion Cycle | B29: Inventory Days+Receivable Days-Payable Days | C29: =C26+C27-C28 -> -28.88092 | D29: =D26+D27-D28 -> -23.691215 | E29: =E26+E27-E28 -> -21.458935 | F29: =F26+F27-F28 -> -20.18176 | G29: =G26+G27-G28 -> -21.43854 | H29: =H26+H27-H28 -> -23.74294 | I29: 50 | J29: =IF(C29<I54, "Better than Benchmark", IF(C29>I29,"Worse than Benchmark", "At Benchmark")) -> Better than Benchmark
A31: LEVERAGE/SOLVENCY RATIOS
A32: Ratios | B32: Formula | C32: FY26 | D32: FY25 | E32: FY24 | F32: FY23 | G32: FY22 | H32: FY21 | I32: Benchmark | J32: Comment
A33: Debt to Equity | B33: Total Debt/Total Equity | C33: =('Balance sheet'!B42+'Balance sheet'!B44+'Balance sheet'!B52)/'Balance sheet'!B39 -> 0.10401187 | D33: =('Balance sheet'!C42+'Balance sheet'!C44+'Balance sheet'!C52)/'Balance sheet'!C39 -> 0.098067265 | E33: =('Balance sheet'!D42+'Balance sheet'!D44+'Balance sheet'!D52)/'Balance sheet'!D39 -> 0.035713375 | F33: =('Balance sheet'!E42+'Balance sheet'!E44+'Balance sheet'!E52)/'Balance sheet'!E39 -> 0.039207087 | G33: =('Balance sheet'!F42+'Balance sheet'!F44+'Balance sheet'!F52)/'Balance sheet'!F39 -> 0.041704124 | H33: =('Balance sheet'!G42+'Balance sheet'!G44+'Balance sheet'!G52)/'Balance sheet'!G39 -> 0.046945014 | I33: 0.1 | J33: =IF(C33<I33, "Better than Benchmark", IF(C33>I33,"Worse than Benchmark", "At Benchmark")) -> Worse than Benchmark
A34: Debt Ratio | B34: Total Liabilities/Total Assets | C34: ='Balance sheet'!B57/'Balance sheet'!B32 -> 0.40518281 | D34: ='Balance sheet'!C57/'Balance sheet'!C32 -> 0.40004009 | E34: ='Balance sheet'!D57/'Balance sheet'!D32 -> 0.45234787 | F34: ='Balance sheet'!E57/'Balance sheet'!E32 -> 0.44458415 | G34: ='Balance sheet'!F57/'Balance sheet'!F32 -> 0.42573867 | H34: ='Balance sheet'!G57/'Balance sheet'!G32 -> 0.43643535 | I34: 0.1 | J34: =IF(C34<I34, "Better than Benchmark", IF(B3>C33,"Worse than Benchmark", "At Benchmark")) -> Worse than Benchmark
A35: Equity Ratio | B35: Total Equity/Total Assets | C35: ='Balance sheet'!B39/'Balance sheet'!B32 -> 0.59481719 | D35: ='Balance sheet'!C39/'Balance sheet'!C32 -> 0.59995991 | E35: ='Balance sheet'!D39/'Balance sheet'!D32 -> 0.90099794 | F35: ='Balance sheet'!E39/'Balance sheet'!E32 -> 0.89595285 | G35: ='Balance sheet'!F39/'Balance sheet'!F32 -> 0.85495933 | H35: ='Balance sheet'!G39/'Balance sheet'!G32 -> 0.89941032 | I35: 0.8 | J35: =IF(C35>I35,"Above Benchmark", IF(C35<I35,"Below Benchmark","At Benchmark")) -> Below Benchmark
A36: Interest Coverage Ratio | B36: EBIT/Finance Cost | C36: =Historical_IS!B6/'Cash Flow'!B22 -> 54.472698 | D36: =Historical_IS!C6/'Cash Flow'!C22 -> 78.096734 | E36: =Historical_IS!D6/'Cash Flow'!D22 -> 76.235219 | F36: =Historical_IS!E6/'Cash Flow'!E22 -> 69.623877 | G36: =Historical_IS!F6/'Cash Flow'!F22 -> 61.802296 | H36: =Historical_IS!G6/'Cash Flow'!G22 -> 66.689168 | I36: 50 | J36: =IF(C36>I36,"Above Benchmark", IF(C36<I36,"Below Benchmark","At Benchmark")) -> Above Benchmark
A37: Financial Leverage | B37: Average Total Assets/Average Equity | C37: =AVERAGE('Balance sheet'!B32,'Balance sheet'!C32)/AVERAGE('Balance sheet'!B39,'Balance sheet'!C39) -> 1.6744317 | D37: =AVERAGE('Balance sheet'!C32,'Balance sheet'!D32)/AVERAGE('Balance sheet'!C39,'Balance sheet'!D39) -> 1.3209504 | E37: =AVERAGE('Balance sheet'!D32,'Balance sheet'!E32)/AVERAGE('Balance sheet'!D39,'Balance sheet'!E39) -> 1.1127914 | F37: =AVERAGE('Balance sheet'!E32,'Balance sheet'!F32)/AVERAGE('Balance sheet'!E39,'Balance sheet'!F39) -> 1.14199 | G37: =AVERAGE('Balance sheet'!F32,'Balance sheet'!G32)/AVERAGE('Balance sheet'!F39,'Balance sheet'!G39) -> 1.1422612 | H37: =AVERAGE('Balance sheet'!G32,'Balance sheet'!H32)/AVERAGE('Balance sheet'!G39,'Balance sheet'!H39) -> 1.1118396 | I37: 1.25 | J37: =IF(C37<I62, "Better than Benchmark", IF(C37>I37,"Worse than Benchmark", "At Benchmark")) -> Worse than Benchmark
A39: RETURN RATIOS
A40: Ratios | B40: Formula | C40: FY26 | D40: FY25 | E40: FY24 | F40: FY23 | G40: FY22 | H40: FY21 | I40: Benchmark | J40: Comment
A41: Return on Equity(ROE) | B41: PAT/Average Equity | C41: =Historical_IS!B8/AVERAGE('Balance sheet'!B39,'Balance sheet'!C39) -> 0.51721183 | D41: =Historical_IS!C8/AVERAGE('Balance sheet'!C39,'Balance sheet'!D39) -> 0.38429361 | E41: =Historical_IS!D8/AVERAGE('Balance sheet'!D39,'Balance sheet'!E39) -> 0.31719822 | F41: =Historical_IS!E8/AVERAGE('Balance sheet'!E39,'Balance sheet'!F39) -> 0.31840657 | G41: =Historical_IS!F8/AVERAGE('Balance sheet'!F39,'Balance sheet'!G39) -> 0.31534345 | H41: =Historical_IS!G8/AVERAGE('Balance sheet'!G39,'Balance sheet'!H39) -> 0.28993713 | I41: 0.3 | J41: =IF(C41>I41,"Above Benchmark", IF(C41<I41,"Below Benchmark","At Benchmark")) -> Above Benchmark
A42: Return on Asset(ROA) | B42: PAT/Average Total Assets | C42: =Historical_IS!B8/AVERAGE('Balance sheet'!B32,'Balance sheet'!C32) -> 0.30888799 | D42: =Historical_IS!C8/AVERAGE('Balance sheet'!C32,'Balance sheet'!D32) -> 0.29092206 | E42: =Historical_IS!D8/AVERAGE('Balance sheet'!D32,'Balance sheet'!E32) -> 0.28504733 | F42: =Historical_IS!E8/AVERAGE('Balance sheet'!E32,'Balance sheet'!F32) -> 0.27881731 | G42: =Historical_IS!F8/AVERAGE('Balance sheet'!F32,'Balance sheet'!G32) -> 0.27606947 | H42: =Historical_IS!G8/AVERAGE('Balance sheet'!G32,'Balance sheet'!H32) -> 0.26077245 | I42: 0.23 | J42: =IF(C42>I42,"Above Benchmark", IF(C42<I42,"Below Benchmark","At Benchmark")) -> Above Benchmark
A43: Return on Capital Employed(ROCE) | B43: EBIT/Average(Total Assets - Current Liabilities) | C43: =Historical_IS!B6/AVERAGE(('Balance sheet'!B32-'Balance sheet'!B55),('Balance sheet'!C32-'Balance sheet'!C55)) -> 0.58607718 | D43: =Historical_IS!C6/AVERAGE(('Balance sheet'!C32-'Balance sheet'!C55),('Balance sheet'!D32-'Balance sheet'!D55)) -> 0.59812859 | E43: =Historical_IS!D6/AVERAGE(('Balance sheet'!D32-'Balance sheet'!D55),('Balance sheet'!E32-'Balance sheet'!E55)) -> 0.61791303 | F43: =Historical_IS!E6/AVERAGE(('Balance sheet'!E32-'Balance sheet'!E55),('Balance sheet'!F32-'Balance sheet'!F55)) -> 0.5944074 | G43: =Historical_IS!F6/AVERAGE(('Balance sheet'!F32-'Balance sheet'!F55),('Balance sheet'!G32-'Balance sheet'!G55)) -> 0.57164262 | H43: =Historical_IS!G6/AVERAGE(('Balance sheet'!G32-'Balance sheet'!G55),('Balance sheet'!H32-'Balance sheet'!H55)) -> 1.092534 | I43: 0.38 | J43: =IF(C43>I43,"Above Benchmark", IF(C43<I43,"Below Benchmark","At Benchmark")) -> Above Benchmark
A45: MARKET RATIOS
A46: Ratios | B46: Formula | C46: FY26 | D46: FY25 | E46: FY24 | F46: FY23 | G46: FY22 | H46: FY21 | I46: Benchmark | J46: Comment
A47: Earning Per Share(EPS) | B47: PAT/Weighted average no. of shares | C47: =Historical_IS!B9 -> 145.99 | D47: =Historical_IS!C9 -> 134.19 | E47: =Historical_IS!D9 -> 127.74 | F47: =Historical_IS!E9 -> 115.19 | G47: =Historical_IS!F9 -> 103.62 | H47: =Historical_IS!G9 -> 89.27 | I47: Positive and Growing | J47: =IF(C47>0,"Healthy",IF(C47<0,"Negative","Break-even")) -> Healthy
A48: Current Share Price | C48: 2230.9 | D48: 2231.9 | E48: 2232.9 | F48: 2233.9 | G48: 2234.9 | H48: 2235.9 | J48: Market determined
A49: Price-to-Earnings(P/E) Ratio | B49: Market Price per share/EPS | C49: =C48/Historical_IS!B9 -> 15.281184 | D49: =D48/Historical_IS!C9 -> 16.632387 | E49: =E48/Historical_IS!D9 -> 17.480038 | F49: =F48/Historical_IS!E9 -> 19.393176 | G49: =G48/Historical_IS!F9 -> 21.56823 | H49: =H48/Historical_IS!G9 -> 25.046488 | I49: 28 | J49: =IF(C49>I49,"Above Benchmark", IF(C49<I49,"Below Benchmark","At Benchmark")) -> Below Benchmark
A50: Book Value Per Share(BVPS) | B50: Equity/Shares Outstanding | C50: ='Balance sheet'!B39/361.8087518 -> 299.82138 | D50: ='Balance sheet'!C39/361.8087518 -> 264.70062 | E50: ='Balance sheet'!D39/361.8087518 -> 433.69874 | F50: ='Balance sheet'!E39/361.8087518 -> 378.13347 | G50: ='Balance sheet'!F39/361.8087518 -> 353.57077 | H50: ='Balance sheet'!G39/361.8087518 -> 318.27865 | I50: 250 | J50: =IF(C50>I50,"Above Benchmark", IF(C50<I50,"Below Benchmark","At Benchmark")) -> Above Benchmark
A51: Price to Book Ratio | B51: Current shsare price /BVPS | C51: =C48/C50 -> 7.4407635 | D51: =D48/D50 -> 8.4317899 | E51: =E48/E50 -> 5.1485047 | F51: =F48/F50 -> 5.9077023 | G51: =G48/G50 -> 6.320941 | H51: =H48/H50 -> 7.0249765 | I51: 8
A52: Dividend Per Share (Q1+Q2+Q3+Special Q3+Final) | B52: (11+11+11+11+46+31) | C52: 100 | D52: 101 | E52: 102 | F52: 103 | G52: 104 | H52: 105 | I52: 70 | J52: =IF(C52>I52,"Above Benchmark", IF(C52<I52,"Below Benchmark","At Benchmark")) -> Above Benchmark
A53: Dividend Payout Ratio | B53: Dividend/PAT | C53: =C52/Historical_IS!B9 -> 0.68497842 | D53: =D52/Historical_IS!C9 -> 0.75266413 | E53: =E52/Historical_IS!D9 -> 0.79849695 | F53: =F52/Historical_IS!E9 -> 0.89417484 | G53: =G52/Historical_IS!F9 -> 1.0036672 | H53: =H52/Historical_IS!G9 -> 1.176207 | I53: 0.65 | J53: =IF(C53>I53,"Above Benchmark", IF(C53<I53,"Below Benchmark","At Benchmark")) -> Above Benchmark
A54: Dividend Yield | B54: Dividend Per Share/Market Price Per Share | C54: =C52/C48 -> 0.044824959 | D54: =D52/D48 -> 0.045252924 | E54: =E52/E48 -> 0.045680505 | F54: =F52/F48 -> 0.046107704 | G54: =G52/G48 -> 0.046534521 | H54: =H52/H48 -> 0.046960955 | I54: 0.015 | J54: =IF(C54>I54,"Above Benchmark", IF(C54<I54,"Below Benchmark","At Benchmark")) -> Above Benchmark
A55: Retention Ratio | B55: 1-Dividend Payout | C55: =1-C53 -> 0.31502158 | D55: =1-D53 -> 0.24733587 | E55: =1-E53 -> 0.20150305 | F55: =1-F53 -> 0.10582516 | G55: =1-G53 -> -0.0036672457 | H55: =1-H53 -> -0.17620701 | I55: 0.35 | J55: =IF(C55>I55,"Above Benchmark", IF(C55<I55,"Below Benchmark","At Benchmark")) -> Below Benchmark
A57: CASH FLOW RATIOS
A58: Ratios | B58: Formula | C58: FY26 | D58: FY25 | E58: FY24 | F58: FY23 | G58: FY22 | H58: FY21 | I58: Benchmark | J58: Comment
A59: Operating Cash Flow Ratio | B59: Operating Cash Flow/Current Liabilities | C59: ='Cash Flow'!B34/'Balance sheet'!B55 -> -0.036280658 | D59: ='Cash Flow'!C34/'Balance sheet'!C55 -> -0.063376163 | E59: ='Cash Flow'!D34/'Balance sheet'!D55 -> -0.094376106 | F59: ='Cash Flow'!E34/'Balance sheet'!E55 -> -0.068054547 | G59: ='Cash Flow'!F34/'Balance sheet'!F55 -> -0.047847799 | H59: ='Cash Flow'!G34/'Balance sheet'!G55 -> 0.017167638 | I59: 1.2 | J59: =IF(C59>I59,"Above Benchmark", IF(C59<I59,"Below Benchmark","At Benchmark")) -> Below Benchmark
A60: Cash Flow Margin | B60: Operating Cash Flow/Revenue | C60: ='Cash Flow'!B36/Historical_IS!B2 -> 0.19509327 | D60: ='Cash Flow'!C36/Historical_IS!C2 -> 0.19155269 | E60: ='Cash Flow'!D36/Historical_IS!D2 -> 0.18405682 | F60: ='Cash Flow'!E36/Historical_IS!E2 -> 0.18613223 | G60: ='Cash Flow'!F36/Historical_IS!F2 -> 0.20833464 | H60: ='Cash Flow'!G36/Historical_IS!G2 -> 0.23634248 | I60: 0.2 | J60: =IF(C60>I60,"Above Benchmark", IF(C60<I60,"Below Benchmark","At Benchmark")) -> Below Benchmark
A61: Cash Conversion Ratio | B61: Operating Cash Flow/PAT | C61: ='Cash Flow'!B36/AVERAGE('Balance sheet'!B32,'Balance sheet'!C32) -> 0.30464238 | D61: ='Cash Flow'!C36/AVERAGE('Balance sheet'!C32,'Balance sheet'!D32) -> 0.29304916 | E61: ='Cash Flow'!D36/AVERAGE('Balance sheet'!D32,'Balance sheet'!E32) -> 0.27129824 | F61: ='Cash Flow'!E36/AVERAGE('Balance sheet'!E32,'Balance sheet'!F32) -> 0.27761331 | G61: ='Cash Flow'!F36/AVERAGE('Balance sheet'!F32,'Balance sheet'!G32) -> 0.28775274 | H61: ='Cash Flow'!G36/AVERAGE('Balance sheet'!G32,'Balance sheet'!H32) -> 0.30305776 | I61: 1 | J61: =IF(C61>I61,"Above Benchmark", IF(C61<I61,"Below Benchmark","At Benchmark")) -> Below Benchmark
A62: Cash Return on Equity | B62: Operating Cash Flow/Average Equity | C62: ='Cash Flow'!B36/AVERAGE('Balance sheet'!B39,'Balance sheet'!C39) -> 0.51010286 | D62: ='Cash Flow'!C36/AVERAGE('Balance sheet'!C39,'Balance sheet'!D39) -> 0.38710341 | E62: ='Cash Flow'!D36/AVERAGE('Balance sheet'!D39,'Balance sheet'!E39) -> 0.30189835 | F62: ='Cash Flow'!E36/AVERAGE('Balance sheet'!E39,'Balance sheet'!F39) -> 0.31703162 | G62: ='Cash Flow'!F36/AVERAGE('Balance sheet'!F39,'Balance sheet'!G39) -> 0.32868879 | H62: ='Cash Flow'!G36/AVERAGE('Balance sheet'!G39,'Balance sheet'!H39) -> 0.33695161 | I62: 0.28 | J62: =IF(C62>I62,"Above Benchmark", IF(C62<I62,"Below Benchmark","At Benchmark")) -> Above Benchmark
A63: Free Cash Flow | B63: Operating Cash Flow-CapEx | C63: ='Cash Flow'!B36+'Cash Flow'!B45 -> 48424 | D63: ='Cash Flow'!C36+'Cash Flow'!C45 -> 45991 | E63: ='Cash Flow'!D36+'Cash Flow'!D45 -> 42136 | F63: ='Cash Flow'!E36+'Cash Flow'!E45 -> 39433 | G63: ='Cash Flow'!F36+'Cash Flow'!F45 -> 37466 | H63: ='Cash Flow'!G36+'Cash Flow'!G45 -> 36083 | I63: Positive | J63: =IF(C63>0,"Healthy",IF(C63<0,"Negative","Break-even")) -> Healthy
A64: Free Cash Flow Margin | B64: FCF/Revenue | C64: =C63/Historical_IS!B2 -> 0.18134903 | D64: =D63/Historical_IS!C2 -> 0.18012799 | E64: =E63/Historical_IS!D2 -> 0.17491583 | F64: =F63/Historical_IS!E2 -> 0.17490176 | G64: =G63/Historical_IS!F2 -> 0.19538575 | H64: =H63/Historical_IS!G2 -> 0.21978109 | I64: 0.18 | J64: =IF(C64>I64,"Above Benchmark", IF(C64<I64,"Below Benchmark","At Benchmark")) -> Above Benchmark
A65: CapEx Ratio | B65: CapEx/Operating Cash Flow | C65: ='Cash Flow'!B45/'Cash Flow'!B36 -> -0.070449572 | D65: ='Cash Flow'!C45/'Cash Flow'!C36 -> -0.059642594 | E65: ='Cash Flow'!D45/'Cash Flow'!D36 -> -0.049663945 | F65: ='Cash Flow'!E45/'Cash Flow'!E36 -> -0.060335994 | G65: ='Cash Flow'!F45/'Cash Flow'!F36 -> -0.062154247 | H65: ='Cash Flow'!G45/'Cash Flow'!G36 -> -0.070073708 | I65: 0.03 | J65: =IF(C65>I65,"Above Benchmark", IF(C65<I65,"Below Benchmark","At Benchmark")) -> Below Benchmark
A67: GROWTH RATIOS
A68: Ratios | B68: Formula | C68: FY26 | D68: FY25 | E68: FY24 | F68: FY23 | G68: FY22 | H68: FY21 | I68: Benchmark | J68: Comment
A69: Revenue Growth | B69: (Current Revenue - Previous Revenue) / Previous Revenue | C69: =(Historical_IS!B2-Historical_IS!C2)/Historical_IS!C2 -> 0.04581238 | D69: =(Historical_IS!C2-Historical_IS!D2)/Historical_IS!D2 -> 0.059906265 | E69: =(Historical_IS!D2-Historical_IS!E2)/Historical_IS!E2 -> 0.068460645 | F69: =(Historical_IS!E2-Historical_IS!F2)/Historical_IS!F2 -> 0.17576687 | G69: =(Historical_IS!F2-Historical_IS!G2)/Historical_IS!G2 -> 0.16797115 | I69: 0.08 | J69: =IF(C69>I69,"Above Benchmark", IF(C69<I69,"Below Benchmark","At Benchmark")) -> Below Benchmark
A70: EBIT Growth | C70: =(Historical_IS!B8-Historical_IS!C8)/Historical_IS!C8 -> 0.087883344 | D70: =(Historical_IS!C8-Historical_IS!D8)/Historical_IS!D8 -> 0.042245358 | E70: =(Historical_IS!D8-Historical_IS!E8)/Historical_IS!E8 -> 0.10529812 | F70: =(Historical_IS!E8-Historical_IS!F8)/Historical_IS!F8 -> 0.099668641 | G70: =(Historical_IS!F8-Historical_IS!G8)/Historical_IS!G8 -> 0.1479274 | I70: 0.08 | J70: =IF(C70>I70,"Above Benchmark", IF(C70<I70,"Below Benchmark","At Benchmark")) -> Above Benchmark
A71: PAT Growth | C71: =(Historical_IS!B8-Historical_IS!C8)/Historical_IS!C8 -> 0.087883344 | D71: =(Historical_IS!C8-Historical_IS!D8)/Historical_IS!D8 -> 0.042245358 | E71: =(Historical_IS!D8-Historical_IS!E8)/Historical_IS!E8 -> 0.10529812 | F71: =(Historical_IS!E8-Historical_IS!F8)/Historical_IS!F8 -> 0.099668641 | G71: =(Historical_IS!F8-Historical_IS!G8)/Historical_IS!G8 -> 0.1479274 | I71: 0.08 | J71: =IF(C71>I71,"Above Benchmark", IF(C71<I71,"Below Benchmark","At Benchmark")) -> Above Benchmark
A72: EPS Growth | C72: =(Historical_IS!B9-Historical_IS!C9)/Historical_IS!C9 -> 0.087935018 | D72: =(Historical_IS!C9-Historical_IS!D9)/Historical_IS!D9 -> 0.050493189 | E72: =(Historical_IS!D9-Historical_IS!E9)/Historical_IS!E9 -> 0.10895043 | F72: =(Historical_IS!E9-Historical_IS!F9)/Historical_IS!F9 -> 0.11165798 | G72: =(Historical_IS!F9-Historical_IS!G9)/Historical_IS!G9 -> 0.16074829 | I72: 0.1 | J72: =IF(C72>I72,"Above Benchmark", IF(C72<I72,"Below Benchmark","At Benchmark")) -> Below Benchmark
A73: Asset Growth | C73: =('Balance sheet'!B32-'Balance sheet'!C32)/'Balance sheet'!C32 -> 0.14247411 | D73: =('Balance sheet'!C32-'Balance sheet'!D32)/'Balance sheet'!D32 -> -0.083424247 | E73: =('Balance sheet'!D32-'Balance sheet'!E32)/'Balance sheet'!E32 -> 0.1405239 | F73: =('Balance sheet'!E32-'Balance sheet'!F32)/'Balance sheet'!F32 -> 0.020537737 | G73: =('Balance sheet'!F32-'Balance sheet'!G32)/'Balance sheet'!G32 -> 0.16864139 | I73: 0.08 | J73: =IF(C73>I73,"Above Benchmark", IF(C73<I73,"Below Benchmark","At Benchmark")) -> Above Benchmark
A74: Equity Growth | C74: =('Balance sheet'!B39-'Balance sheet'!C39)/'Balance sheet'!C39 -> 0.13268108 | D74: =('Balance sheet'!C39-'Balance sheet'!D39)/'Balance sheet'!D39 -> -0.38966708 | E74: =('Balance sheet'!D39-'Balance sheet'!E39)/'Balance sheet'!E39 -> 0.14694617 | F74: =('Balance sheet'!E39-'Balance sheet'!F39)/'Balance sheet'!F39 -> 0.069470393 | G74: =('Balance sheet'!F39-'Balance sheet'!G39)/'Balance sheet'!G39 -> 0.11088437 | I74: 0.08 | J74: =IF(C74>I74,"Above Benchmark", IF(C74<I74,"Below Benchmark","At Benchmark")) -> Above Benchmark
A75: Operating Cash Flow Growth | C75: =('Cash Flow'!B36-'Cash Flow'!C36)/'Cash Flow'!C36 -> 0.065142717 | D75: =('Cash Flow'!C36-'Cash Flow'!D36)/'Cash Flow'!D36 -> 0.10307186 | E75: =('Cash Flow'!D36-'Cash Flow'!E36)/'Cash Flow'!E36 -> 0.056547123 | F75: =('Cash Flow'!E36-'Cash Flow'!F36)/'Cash Flow'!F36 -> 0.050464342 | G75: =('Cash Flow'!F36-'Cash Flow'!G36)/'Cash Flow'!G36 -> 0.029560332 | I75: 0.1 | J75: =IF(C75>I75,"Above Benchmark", IF(C75<I75,"Below Benchmark","At Benchmark")) -> Below Benchmark

Sheet Trend Analysis
A1: TREND ANALYSIS SHEET
A4: REVENUE TREND
A5: Metric | B5: FY26 | C5: FY25 | D5: FY24 | E5: FY23 | F5: FY22 | G5: FY21
A6: Revenue | B6: =Historical_IS!B2 -> 267021 | C6: =Historical_IS!C2 -> 255324 | D6: =Historical_IS!D2 -> 240893 | E6: =Historical_IS!E2 -> 225458 | F6: =Historical_IS!F2 -> 191754 | G6: =Historical_IS!G2 -> 164177
A7: Revenue Index(FY21=100) | B7: =Historical_IS!B2/Historical_IS!G2*100 -> 162.64215 | C7: =Historical_IS!C2/Historical_IS!G2*100 -> 155.51752 | D7: =Historical_IS!D2/Historical_IS!G2*100 -> 146.72762 | E7: =Historical_IS!E2/Historical_IS!G2*100 -> 137.32618 | F7: =Historical_IS!F2/Historical_IS!G2*100 -> 116.79712 | G7: 100
A9: COST TREND
A10: Metric | B10: FY26 | C10: FY25 | D10: FY24 | E10: FY23 | F10: FY22 | G10: FY21
A11: Employee Cost | B11: =Historical_IS!B3 -> 154994 | C11: =Historical_IS!C3 -> 145788 | D11: =Historical_IS!D3 -> 140131 | E11: =Historical_IS!E3 -> 127522 | F11: =Historical_IS!F3 -> 107554 | G11: =Historical_IS!G3 -> 91814
A12: Other Operating Cost | B12: =Historical_IS!B4 -> 45189 | C12: =Historical_IS!C4 -> 47371 | D12: =Historical_IS!D4 -> 41451 | E12: =Historical_IS!E4 -> 43699 | F12: =Historical_IS!F4 -> 35747 | G12: =Historical_IS!G4 -> 29882
A13: Operating Cost | B13: =Historical_IS!B5 -> 200183 | C13: =Historical_IS!C5 -> 193159 | D13: =Historical_IS!D5 -> 181582 | E13: =Historical_IS!E5 -> 171221 | F13: =Historical_IS!F5 -> 143301 | G13: =Historical_IS!G5 -> 121696
A15: PROFIT TREND
A16: Metric | B16: FY26 | C16: FY25 | D16: FY24 | E16: FY23 | F16: FY22 | G16: FY21
A17: EBIT | B17: =Historical_IS!B6 -> 66838 | C17: =Historical_IS!C6 -> 62165 | D17: =Historical_IS!D6 -> 59311 | E17: =Historical_IS!E6 -> 54237 | F17: =Historical_IS!F6 -> 48453 | G17: =Historical_IS!G6 -> 42481
A18: PBT | B18: =Historical_IS!B7 -> 70355 | C18: =Historical_IS!C7 -> 65331 | D18: =Historical_IS!D7 -> 63038 | E18: =Historical_IS!E7 -> 56907 | F18: =Historical_IS!F7 -> 51687 | G18: =Historical_IS!G7 -> 44978
A19: PAT | B19: =Historical_IS!B8 -> 52820 | C19: =Historical_IS!C8 -> 48553 | D19: =Historical_IS!D8 -> 46585 | E19: =Historical_IS!E8 -> 42147 | F19: =Historical_IS!F8 -> 38327 | G19: =Historical_IS!G8 -> 33388
A20: EPS | B20: =Historical_IS!B9 -> 145.99 | C20: =Historical_IS!C9 -> 134.19 | D20: =Historical_IS!D9 -> 127.74 | E20: =Historical_IS!E9 -> 115.19 | F20: =Historical_IS!F9 -> 103.62 | G20: =Historical_IS!G9 -> 89.27
A22: ASSET TREND
A23: Metric | B23: FY26 | C23: FY25 | D23: FY24 | E23: FY23 | F23: FY22 | G23: FY21
A24: Total Assets | B24: ='Balance sheet'!B32 -> 182372 | C24: ='Balance sheet'!C32 -> 159629 | D24: ='Balance sheet'!D32 -> 174158 | E24: ='Balance sheet'!E32 -> 152700 | F24: ='Balance sheet'!F32 -> 149627 | G24: ='Balance sheet'!G32 -> 128035
A25: Current Assets | B25: ='Balance sheet'!B30 -> 135705 | C25: ='Balance sheet'!C30 -> 123011 | D25: ='Balance sheet'!D30 -> 113610 | E25: ='Balance sheet'!E30 -> 92784 | F25: ='Balance sheet'!F30 -> 94192 | G25: ='Balance sheet'!G30 -> 83160
A26: Non-current Assets | B26: ='Balance sheet'!B18 -> 46667 | C26: ='Balance sheet'!C18 -> 36618 | D26: ='Balance sheet'!D18 -> 60548 | E26: ='Balance sheet'!E18 -> 59916 | F26: ='Balance sheet'!F18 -> 55435 | G26: ='Balance sheet'!G18 -> 44875
A27: Cash & Cash Equivalents | B27: ='Balance sheet'!B24 -> 6417 | C27: ='Balance sheet'!C24 -> 8342 | D27: ='Balance sheet'!D24 -> 4907 | E27: ='Balance sheet'!E24 -> 1462 | F27: ='Balance sheet'!F24 -> 8197 | G27: ='Balance sheet'!G24 -> 1112
A28: Trade Receivables | B28: ='Balance sheet'!B12 -> 213 | C28: ='Balance sheet'!C12 -> 129 | D28: ='Balance sheet'!D12 -> 2530 | E28: ='Balance sheet'!E12 -> 2215 | F28: ='Balance sheet'!F12 -> 1588 | G28: ='Balance sheet'!G12 -> 1221
A29: PPE | B29: ='Balance sheet'!B6 -> 11032 | C29: ='Balance sheet'!C6 -> 10978 | D29: ='Balance sheet'!D6 -> 11648 | E29: ='Balance sheet'!E6 -> 10467 | F29: ='Balance sheet'!F6 -> 9634 | G29: ='Balance sheet'!G6 -> 8702
A30: Goodwill | B30: ='Balance sheet'!B9 -> 9108 | C30: ='Balance sheet'!C9 -> 1860 | D30: ='Balance sheet'!D9 -> 5755 | E30: ='Balance sheet'!E9 -> 5571 | F30: ='Balance sheet'!F9 -> 5298 | G30: ='Balance sheet'!G9 -> 4947
A32: LIABILITY TREND
A33: Metric | B33: FY26 | C33: FY25 | D33: FY24 | E33: FY23 | F33: FY22 | G33: FY21
A34: Total Liabilities | B34: ='Balance sheet'!B57 -> 73894 | C34: ='Balance sheet'!C57 -> 63858 | D34: ='Balance sheet'!D57 -> 78780 | E34: ='Balance sheet'!E57 -> 67888 | F34: ='Balance sheet'!F57 -> 63702 | G34: ='Balance sheet'!G57 -> 55879
A35: Curren Liabilities | B35: ='Balance sheet'!B55 -> 60914 | C35: ='Balance sheet'!C55 -> 53001 | D35: ='Balance sheet'!D55 -> 72921 | E35: ='Balance sheet'!E55 -> 61965 | F35: ='Balance sheet'!F55 -> 57871 | G35: ='Balance sheet'!G55 -> 50269
A36: Non-current Liabilities | B36: ='Balance sheet'!B47 -> 12980 | C36: ='Balance sheet'!C47 -> 10857 | D36: ='Balance sheet'!D47 -> 5859 | E36: ='Balance sheet'!E47 -> 5923 | F36: ='Balance sheet'!F47 -> 5831 | G36: ='Balance sheet'!G47 -> 5610
A37: Lease Liabilities | B37: ='Balance sheet'!B44+'Balance sheet'!B52 -> 11283 | C37: ='Balance sheet'!C44+'Balance sheet'!C52 -> 9392 | D37: ='Balance sheet'!D44+'Balance sheet'!D52 -> 5604 | E37: ='Balance sheet'!E44+'Balance sheet'!E52 -> 5364 | F37: ='Balance sheet'!F44+'Balance sheet'!F52 -> 5335 | G37: ='Balance sheet'!G44+'Balance sheet'!G52 -> 5406
A38: Trade Payables | B38: ='Balance sheet'!B50 -> 14808 | C38: ='Balance sheet'!C50 -> 13909 | D38: ='Balance sheet'!D50 -> 8369 | E38: ='Balance sheet'!E50 -> 8158 | F38: ='Balance sheet'!F50 -> 7466 | G38: ='Balance sheet'!G50 -> 6313
A40: EQUITY TREND
A41: Metric | B41: FY26 | C41: FY25 | D41: FY24 | E41: FY23 | F41: FY22 | G41: FY21
A42: Total Equity | B42: ='Balance sheet'!B39 -> 108478 | C42: ='Balance sheet'!C39 -> 95771 | D42: ='Balance sheet'!D39 -> 156916 | E42: ='Balance sheet'!E39 -> 136812 | F42: ='Balance sheet'!F39 -> 127925 | G42: ='Balance sheet'!G39 -> 115156
A43: Total Capital | B43: ='Balance sheet'!B37 -> 362 | C43: ='Balance sheet'!C37 -> 362 | D43: ='Balance sheet'!D37 -> 362 | E43: ='Balance sheet'!E37 -> 362 | F43: ='Balance sheet'!F37 -> 362 | G43: ='Balance sheet'!G37 -> 362
A44: Other Equity | B44: ='Balance sheet'!B38 -> 106878 | C44: ='Balance sheet'!C38 -> 94394 | D44: ='Balance sheet'!D38 -> 156529 | E44: ='Balance sheet'!E38 -> 136431 | F44: ='Balance sheet'!F38 -> 127547 | G44: ='Balance sheet'!G38 -> 114778
A45: Book Value | B45: ='Balance sheet'!B39 -> 108478 | C45: ='Balance sheet'!C39 -> 95771 | D45: ='Balance sheet'!D39 -> 156916 | E45: ='Balance sheet'!E39 -> 136812 | F45: ='Balance sheet'!F39 -> 127925 | G45: ='Balance sheet'!G39 -> 115156
A47: CASH FLOW TREND
A48: Metric | B48: FY26 | C48: FY25 | D48: FY24 | E48: FY23 | F48: FY22 | G48: FY21
A49: Operating Cash Flow | B49: ='Cash Flow'!B36 -> 52094 | C49: ='Cash Flow'!C36 -> 48908 | D49: ='Cash Flow'!D36 -> 44338 | E49: ='Cash Flow'!E36 -> 41965 | F49: ='Cash Flow'!F36 -> 39949 | G49: ='Cash Flow'!G36 -> 38802
A50: Investing Cash Flow | B50: ='Cash Flow'!B63 -> -12845 | C50: ='Cash Flow'!C63 -> -2318 | D50: ='Cash Flow'!D63 -> 6019 | E50: ='Cash Flow'!E63 -> 39 | F50: ='Cash Flow'!F63 -> -897 | G50: ='Cash Flow'!G63 -> -8129
A51: Financing Cash Flow | B51: ='Cash Flow'!B77 -> -42133 | C51: ='Cash Flow'!C77 -> -47438 | D51: ='Cash Flow'!D77 -> -45082 | E51: ='Cash Flow'!E77 -> -43819 | F51: ='Cash Flow'!F77 -> -40546 | G51: ='Cash Flow'!G77 -> -34947
A52: Free Cash Flow | B52: ='Cash Flow'!B36+'Cash Flow'!B45 -> 48424 | C52: ='Cash Flow'!C36+'Cash Flow'!C45 -> 45991 | D52: ='Cash Flow'!D36+'Cash Flow'!D45 -> 42136 | E52: ='Cash Flow'!E36+'Cash Flow'!E45 -> 39433 | F52: ='Cash Flow'!F36+'Cash Flow'!F45 -> 37466 | G52: ='Cash Flow'!G36+'Cash Flow'!G45 -> 36083

Sheet Dashboard
A1: FY21 | FY22 | FY23 | FY24 | FY25 | FY26

Sheet Pivot tables
B3: Column Labels | H3: Column Labels
A4: Values | B4: EBIT Margin | C4: EBITDA Margin | D4: Net Profit Margin | E4: Grand Total | G4: Values | H4: EPS Growth | I4: PAT Growth | J4: Revenue Growth | K4: Grand Total
A5: 2026 | B5: 0.2503099 | C5: 0.27113223 | D5: 0.19781216 | E5: 0.71925429 | G5: 2026 | H5: 0.087935018 | I5: 0.087883344 | J5: 0.04581238 | K5: 0.22163074
A6: 2025 | B6: 0.24347496 | C6: 0.26400573 | D6: 0.1901623 | E6: 0.69764299 | G6: 2025 | H6: 0.050493189 | I6: 0.042245358 | J6: 0.059906265 | K6: 0.15264481
A7: 2024 | B7: 0.24621305 | C7: 0.26690688 | D7: 0.19338461 | E7: 0.70650455 | G7: 2024 | H7: 0.10895043 | I7: 0.10529812 | J7: 0.068460645 | K7: 0.2827092
A8: 2023 | B8: 0.24056365 | C8: 0.26283831 | D8: 0.18693947 | E8: 0.69034144 | G8: 2023 | H8: 0.11165798 | I8: 0.099668641 | J8: 0.17576687 | K8: 0.38709349
A9: 2022 | B9: 0.25268313 | C9: 0.27669305 | D9: 0.19987588 | E9: 0.72925206 | G9: 2022 | H9: 0.16074829 | I9: 0.1479274 | J9: 0.16797115 | K9: 0.47664684
A10: 2021 | B10: 0.25875123 | C10: 0.28351109 | D10: 0.20336588 | E10: 0.74562819
A13: Particulars | B13: FY26 | C13: FY25 | D13: FY24 | E13: FY23 | F13: FY22 | G13: FY21
A14: Non-current Assets | B14: 46667 | C14: 36618 | D14: 60548 | E14: 59916 | F14: 55435 | G14: 44875
A15: Current Assets | B15: 135705 | C15: 123011 | D15: 113610 | E15: 92784 | F15: 94192 | G15: 83160
A16: Equity | B16: 108478 | C16: 95771 | D16: 156916 | E16: 136812 | F16: 127925 | G16: 115156
A17: Non-current Liabilities | B17: 12980 | C17: 10857 | D17: 5859 | E17: 5923 | F17: 5831 | G17: 5610
A18: Current Liabilities | B18: 60914 | C18: 53001 | D18: 72921 | E18: 61965 | F18: 57871 | G18: 50269
A20: Particulars | B20: FY26 | C20: FY25 | D20: FY24 | E20: FY23 | F20: FY22 | G20: FY21
A21: Operating CF | B21: ='Cash Flow'!B36 -> 52094 | C21: ='Cash Flow'!C36 -> 48908 | D21: ='Cash Flow'!D36 -> 44338 | E21: ='Cash Flow'!E36 -> 41965 | F21: ='Cash Flow'!F36 -> 39949 | G21: ='Cash Flow'!G36 -> 38802
A22: Investing CF | B22: ='Cash Flow'!B63 -> -12845 | C22: ='Cash Flow'!C63 -> -2318 | D22: ='Cash Flow'!D63 -> 6019 | E22: ='Cash Flow'!E63 -> 39 | F22: ='Cash Flow'!F63 -> -897 | G22: ='Cash Flow'!G63 -> -8129
A23: Financing CF | B23: ='Cash Flow'!B77 -> -42133 | C23: ='Cash Flow'!C77 -> -47438 | D23: ='Cash Flow'!D77 -> -45082 | E23: ='Cash Flow'!E77 -> -43819 | F23: ='Cash Flow'!F77 -> -40546 | G23: ='Cash Flow'!G77 -> -34947
B25: Column Labels
A26: Values | B26: Return on Asset(ROA) | C26: Return on Capital Employed(ROCE) | D26: Return on Equity(ROE) | E26: Grand Total
A27: 2026 | B27: 0.30888799 | C27: 0.58607718 | D27: 0.51721183 | E27: 1.412177
A28: 2025 | B28: 0.29092206 | C28: 0.59812859 | D28: 0.38429361 | E28: 1.2733443
A29: 2024 | B29: 0.28504733 | C29: 0.61791303 | D29: 0.31719822 | E29: 1.2201586
A30: 2023 | B30: 0.27881731 | C30: 0.5944074 | D30: 0.31840657 | E30: 1.1916313
A31: 2022 | B31: 0.27606947 | C31: 0.57164262 | D31: 0.31534345 | E31: 1.1630555
A32: 2021 | B32: 0.26077245 | C32: 1.092534 | D32: 0.28993713 | E32: 1.6432436
A34: Row Labels | B34: 2021 | C34: 2022 | D34: 2023 | E34: 2024 | F34: 2025 | G34: 2026
A35: Debt Ratio | B35: 0.43643535 | C35: 0.42573867 | D35: 0.44458415 | E35: 0.45234787 | F35: 0.40004009 | G35: 0.40518281
A36: Equity Ratio | B36: 0.89941032 | C36: 0.85495933 | D36: 0.89595285 | E36: 0.90099794 | F36: 0.59995991 | G36: 0.59481719
A37: Grand Total | B37: 1.3358457 | C37: 1.280698 | D37: 1.340537 | E37: 1.3533458 | F37: 1 | G37: 1
B40: Column Labels
A41: Values | B41: ROA | C41: ROCE | D41: ROE | E41: Grand Total
A42: 2026 | B42: 0.30888799 | C42: 0.58607718 | D42: 0.51721183 | E42: 1.412177
A43: 2025 | B43: 0.29092206 | C43: 0.59812859 | D43: 0.38429361 | E43: 1.2733443
A44: 2024 | B44: 0.28504733 | C44: 0.61791303 | D44: 0.31719822 | E44: 1.2201586
A45: 2023 | B45: 0.27881731 | C45: 0.5944074 | D45: 0.31840657 | E45: 1.1916313
A46: 2022 | B46: 0.27606947 | C46: 0.57164262 | D46: 0.31534345 | E46: 1.1630555
A47: 2021 | B47: 0.26077245 | C47: 1.092534 | D47: 0.28993713 | E47: 1.6432436
A49: Row Labels | B49: 2026 | C49: 2025 | D49: 2024 | E49: 2023 | F49: 2022 | G49: 2021
A50: Cash Conversion Cycle | B50: -28.88092 | C50: -23.691215 | D50: -21.458935 | E50: -20.18176 | F50: -21.43854 | G50: -23.74294
A51: Receivable Days | B51: 86.636257 | C51: 73.760095 | D51: 65.869338 | E51: 63.866663 | F51: 63.502965 | G51: 68.076923
A52: Grand Total | B52: 57.755337 | C52: 50.06888 | D52: 44.410403 | E52: 43.684902 | F52: 42.064425 | G52: 44.333984
